{
  "delivery.jpg": {
    "asset_id": "3587bfc525add9ff85aa5861f0273e2e",
    "public_id": "postcube.cz/delivery",
    "version": 1620891353,
    "version_id": "6e03eb11d8e1b77fe1d6ea978c5a94c3",
    "signature": "838aa7bc2cd0ca3adff8c859bb43a3d5c7ac9521",
    "width": 4368,
    "height": 2912,
    "format": "jpg",
    "resource_type": "image",
    "created_at": "2021-05-13T07:35:53Z",
    "tags": [],
    "bytes": 6911516,
    "type": "upload",
    "placeholder": false,
    "url": "http://res.cloudinary.com/topmonks/image/upload/v1620891353/postcube.cz/delivery.jpg",
    "secure_url": "https://res.cloudinary.com/topmonks/image/upload/v1620891353/postcube.cz/delivery.jpg",
    "existing": true,
    "original_filename": "delivery"
  },
  "Lakum.png": {
    "asset_id": "06dff2dd489d4b73c8cae685fa97fef7",
    "public_id": "postcube.cz/Lakum",
    "version": 1621256612,
    "version_id": "cfa6a893d3f7f07c0dc4f88b539d88de",
    "signature": "40007ef3673bf7dd6dd87d60d70adb7d875fc164",
    "width": 1024,
    "height": 1000,
    "format": "png",
    "resource_type": "image",
    "created_at": "2021-05-17T13:03:32Z",
    "tags": [],
    "bytes": 316203,
    "type": "upload",
    "etag": "a7d9a77f03f07ce189b3e6a15eb873af",
    "placeholder": false,
    "url": "http://res.cloudinary.com/topmonks/image/upload/v1621256612/postcube.cz/Lakum.png",
    "secure_url": "https://res.cloudinary.com/topmonks/image/upload/v1621256612/postcube.cz/Lakum.png",
    "existing": false,
    "original_filename": "Lakum"
  },
  "TopMonks.png": {
    "asset_id": "ff9a4dce940bb174fe765efbbff9c842",
    "public_id": "postcube.cz/TopMonks",
    "version": 1621256614,
    "version_id": "fc88b5dc85fd414aff1124aab7de954b",
    "signature": "9f1556ca75ef1e19601c276abf17d6d2e14d3883",
    "width": 1024,
    "height": 1000,
    "format": "png",
    "resource_type": "image",
    "created_at": "2021-05-17T13:03:34Z",
    "tags": [],
    "bytes": 70528,
    "type": "upload",
    "etag": "af4a173cae4efa82f196dc534dacdb89",
    "placeholder": false,
    "url": "http://res.cloudinary.com/topmonks/image/upload/v1621256614/postcube.cz/TopMonks.png",
    "secure_url": "https://res.cloudinary.com/topmonks/image/upload/v1621256614/postcube.cz/TopMonks.png",
    "existing": false,
    "original_filename": "TopMonks"
  },
  "choose-pc01.png": {
    "asset_id": "16ae31a8eb95d7f50cff2c42cfb28898",
    "public_id": "postcube.cz/choose-pc01",
    "version": 1620657986,
    "version_id": "ba5e95fea9870fcebc02e613dac32668",
    "signature": "9ae3498290c2029f73c87a2c9e5c73247947c122",
    "width": 1380,
    "height": 868,
    "format": "png",
    "resource_type": "image",
    "created_at": "2021-05-10T14:46:26Z",
    "tags": [],
    "bytes": 1752696,
    "type": "upload",
    "placeholder": false,
    "url": "http://res.cloudinary.com/topmonks/image/upload/v1620657986/postcube.cz/choose-pc01.png",
    "secure_url": "https://res.cloudinary.com/topmonks/image/upload/v1620657986/postcube.cz/choose-pc01.png",
    "existing": true,
    "original_filename": "choose-pc01"
  },
  "choose-pc02.png": {
    "asset_id": "fba0704da5bd9749e4727144718acfda",
    "public_id": "postcube.cz/choose-pc02",
    "version": 1620657985,
    "version_id": "9deb419405e3c02fe0ecf470ae3a58f0",
    "signature": "07afc7e817034a1a3c9a549fae090752040d9b01",
    "width": 1380,
    "height": 868,
    "format": "png",
    "resource_type": "image",
    "created_at": "2021-05-10T14:46:25Z",
    "tags": [],
    "bytes": 827945,
    "type": "upload",
    "placeholder": false,
    "url": "http://res.cloudinary.com/topmonks/image/upload/v1620657985/postcube.cz/choose-pc02.png",
    "secure_url": "https://res.cloudinary.com/topmonks/image/upload/v1620657985/postcube.cz/choose-pc02.png",
    "existing": true,
    "original_filename": "choose-pc02"
  },
  "contact-map.png": {
    "asset_id": "54293510ed90f860cbe0779efeafcb33",
    "public_id": "postcube.cz/contact-map",
    "version": 1620804984,
    "version_id": "29ccb3406b73936bd0751a965c8de70a",
    "signature": "a395ca396f0e56b3fa144dbb3d7593eb7df3ec3a",
    "width": 2596,
    "height": 1672,
    "format": "png",
    "resource_type": "image",
    "created_at": "2021-05-12T07:36:24Z",
    "tags": [],
    "bytes": 835521,
    "type": "upload",
    "placeholder": false,
    "url": "http://res.cloudinary.com/topmonks/image/upload/v1620804984/postcube.cz/contact-map.png",
    "secure_url": "https://res.cloudinary.com/topmonks/image/upload/v1620804984/postcube.cz/contact-map.png",
    "existing": true,
    "original_filename": "contact-map"
  },
  "create-pc_bg.png": {
    "asset_id": "52c844bfae1aab72103338c69e9d3051",
    "public_id": "postcube.cz/create-pc_bg",
    "version": 1620658169,
    "version_id": "4b702c905f0e07d7a6b7fc689369328c",
    "signature": "10d988c54caa85b27f39340051d70d5167f2da8c",
    "width": 5464,
    "height": 1516,
    "format": "png",
    "resource_type": "image",
    "created_at": "2021-05-10T14:49:29Z",
    "tags": [],
    "bytes": 1779040,
    "type": "upload",
    "placeholder": false,
    "url": "http://res.cloudinary.com/topmonks/image/upload/v1620658169/postcube.cz/create-pc_bg.png",
    "secure_url": "https://res.cloudinary.com/topmonks/image/upload/v1620658169/postcube.cz/create-pc_bg.png",
    "existing": true,
    "original_filename": "create-pc_bg"
  },
  "deliveryman.png": {
    "asset_id": "d6820148e1fb71df4935c403f21c8b8d",
    "public_id": "postcube.cz/deliveryman",
    "version": 1620806015,
    "version_id": "4d50d761352db60f14151e9f57957bb2",
    "signature": "dfa2bba59972c52e4210bbb90fc202fe090136ed",
    "width": 2680,
    "height": 1812,
    "format": "png",
    "resource_type": "image",
    "created_at": "2021-05-12T07:53:35Z",
    "tags": [],
    "bytes": 1485586,
    "type": "upload",
    "placeholder": false,
    "url": "http://res.cloudinary.com/topmonks/image/upload/v1620806015/postcube.cz/deliveryman.png",
    "secure_url": "https://res.cloudinary.com/topmonks/image/upload/v1620806015/postcube.cz/deliveryman.png",
    "existing": true,
    "original_filename": "deliveryman"
  },
  "download-app_bg.png": {
    "asset_id": "f41a82c804ac6bc41e1ba9e71f5ce7ca",
    "public_id": "postcube.cz/download-app_bg",
    "version": 1620380439,
    "version_id": "d4ac5c6ee3c9277013884646431471c6",
    "signature": "c3f20404c08011b0647ced9eb7975c94ec169eca",
    "width": 4904,
    "height": 1685,
    "format": "png",
    "resource_type": "image",
    "created_at": "2021-05-07T09:40:39Z",
    "tags": [],
    "bytes": 37576,
    "type": "upload",
    "placeholder": false,
    "url": "http://res.cloudinary.com/topmonks/image/upload/v1620380439/postcube.cz/download-app_bg.png",
    "secure_url": "https://res.cloudinary.com/topmonks/image/upload/v1620380439/postcube.cz/download-app_bg.png",
    "existing": true,
    "original_filename": "download-app_bg"
  },
  "iphone_bg.png": {
    "asset_id": "bbef7b0913ac5e26f5678c5abd129438",
    "public_id": "postcube.cz/iphone_bg",
    "version": 1620732837,
    "version_id": "718607aba5c3413f79a4c0c16d04333b",
    "signature": "df068986e4cee6e1d62b3a53b58a10006dc7ae64",
    "width": 2348,
    "height": 2796,
    "format": "png",
    "resource_type": "image",
    "created_at": "2021-05-11T11:33:57Z",
    "tags": [],
    "bytes": 4190734,
    "type": "upload",
    "placeholder": false,
    "url": "http://res.cloudinary.com/topmonks/image/upload/v1620732837/postcube.cz/iphone_bg.png",
    "secure_url": "https://res.cloudinary.com/topmonks/image/upload/v1620732837/postcube.cz/iphone_bg.png",
    "existing": true,
    "original_filename": "iphone_bg"
  },
  "jan-slavicek.png": {
    "asset_id": "07d6787cc1a293ac1a4b43bdaaceae0c",
    "public_id": "postcube.cz/jan-slavicek",
    "version": 1621256642,
    "version_id": "087a1953420df09903f844434166f6ba",
    "signature": "f9460b00d48f3c2b6d998b4bf89e2f6318e414be",
    "width": 1025,
    "height": 1000,
    "format": "png",
    "resource_type": "image",
    "created_at": "2021-05-17T13:04:02Z",
    "tags": [],
    "bytes": 589585,
    "type": "upload",
    "etag": "8538a8660c576ad7db9b20cfdc40ff4c",
    "placeholder": false,
    "url": "http://res.cloudinary.com/topmonks/image/upload/v1621256642/postcube.cz/jan-slavicek.png",
    "secure_url": "https://res.cloudinary.com/topmonks/image/upload/v1621256642/postcube.cz/jan-slavicek.png",
    "existing": false,
    "original_filename": "jan-slavicek"
  },
  "section-bg01.png": {
    "asset_id": "e01ea278042accdfe9aa16d13a167809",
    "public_id": "postcube.cz/section-bg01",
    "version": 1620652588,
    "version_id": "dcc284365ce114436597f3286ca7a5c9",
    "signature": "1c4c9eacdf97baf87ea2e58ca3d01e2a3f62f852",
    "width": 2732,
    "height": 1808,
    "format": "png",
    "resource_type": "image",
    "created_at": "2021-05-10T13:16:28Z",
    "tags": [],
    "bytes": 5223873,
    "type": "upload",
    "placeholder": false,
    "url": "http://res.cloudinary.com/topmonks/image/upload/v1620652588/postcube.cz/section-bg01.png",
    "secure_url": "https://res.cloudinary.com/topmonks/image/upload/v1620652588/postcube.cz/section-bg01.png",
    "existing": true,
    "original_filename": "section-bg01"
  },
  "section-bg02.png": {
    "asset_id": "9a64260923d59d8f2a95cec828f6f353",
    "public_id": "postcube.cz/section-bg02",
    "version": 1620652588,
    "version_id": "dcc284365ce114436597f3286ca7a5c9",
    "signature": "b03c498684c3f729bc6003af924b476165b0cebb",
    "width": 2732,
    "height": 1740,
    "format": "png",
    "resource_type": "image",
    "created_at": "2021-05-10T13:16:28Z",
    "tags": [],
    "bytes": 1525320,
    "type": "upload",
    "placeholder": false,
    "url": "http://res.cloudinary.com/topmonks/image/upload/v1620652588/postcube.cz/section-bg02.png",
    "secure_url": "https://res.cloudinary.com/topmonks/image/upload/v1620652588/postcube.cz/section-bg02.png",
    "existing": true,
    "original_filename": "section-bg02"
  },
  "notification-img.png": {
    "asset_id": "f677edd201777a872103467d3538f600",
    "public_id": "postcube.cz/notification-img",
    "version": 1621579337,
    "version_id": "0847a66c25f8657dfbbaf1e0abaae34c",
    "signature": "463984eb3e22e0926df92f52225c5f7933bab0d3",
    "width": 1380,
    "height": 868,
    "format": "png",
    "resource_type": "image",
    "created_at": "2021-05-21T06:42:17Z",
    "tags": [],
    "bytes": 1327588,
    "type": "upload",
    "etag": "54de4431b8d82df924fd8c11c76a79e9",
    "placeholder": false,
    "url": "http://res.cloudinary.com/topmonks/image/upload/v1621579337/postcube.cz/notification-img.png",
    "secure_url": "https://res.cloudinary.com/topmonks/image/upload/v1621579337/postcube.cz/notification-img.png",
    "existing": false,
    "original_filename": "notification-img"
  },
  "mobile-app01.png": {
    "asset_id": "d1eb9ead901ba4e6e8da689a1d6786e7",
    "public_id": "postcube.cz/mobile-app01",
    "version": 1621595017,
    "version_id": "5c7075b7375e7063a253725e9dfa0990",
    "signature": "ab10a7998f23ee6ba675fe493ca7f63706af8cd4",
    "width": 1380,
    "height": 868,
    "format": "png",
    "resource_type": "image",
    "created_at": "2021-05-21T11:03:37Z",
    "tags": [],
    "bytes": 9768,
    "type": "upload",
    "etag": "a0cf4c41bc2a0bb3ac0c6e3b07e64b37",
    "placeholder": false,
    "url": "http://res.cloudinary.com/topmonks/image/upload/v1621595017/postcube.cz/mobile-app01.png",
    "secure_url": "https://res.cloudinary.com/topmonks/image/upload/v1621595017/postcube.cz/mobile-app01.png",
    "existing": false,
    "original_filename": "mobile-app01"
  },
  "mobile-app02.png": {
    "asset_id": "a5dbd7118246abbedfb94073d9db2441",
    "public_id": "postcube.cz/mobile-app02",
    "version": 1621595106,
    "version_id": "9a6bda46d3cab1feb6fe6e1d395f0962",
    "signature": "93b2151dcb4bb2904db6e81a3d557d19e6637bff",
    "width": 1380,
    "height": 868,
    "format": "png",
    "resource_type": "image",
    "created_at": "2021-05-21T11:05:06Z",
    "tags": [],
    "bytes": 7686,
    "type": "upload",
    "etag": "a43b3a9b0043847aac791c09b614fbc9",
    "placeholder": false,
    "url": "http://res.cloudinary.com/topmonks/image/upload/v1621595106/postcube.cz/mobile-app02.png",
    "secure_url": "https://res.cloudinary.com/topmonks/image/upload/v1621595106/postcube.cz/mobile-app02.png",
    "existing": false,
    "original_filename": "mobile-app02"
  },
  "mobile-app03.png": {
    "asset_id": "203c5f44e7b104eaed84a6a67544378b",
    "public_id": "postcube.cz/mobile-app03",
    "version": 1621595108,
    "version_id": "7460d104134dc6fa8edf4471cd08eb0c",
    "signature": "ead58e5a68e5c541bd683294fd20848f70a081df",
    "width": 1380,
    "height": 868,
    "format": "png",
    "resource_type": "image",
    "created_at": "2021-05-21T11:05:08Z",
    "tags": [],
    "bytes": 7686,
    "type": "upload",
    "etag": "a43b3a9b0043847aac791c09b614fbc9",
    "placeholder": false,
    "url": "http://res.cloudinary.com/topmonks/image/upload/v1621595108/postcube.cz/mobile-app03.png",
    "secure_url": "https://res.cloudinary.com/topmonks/image/upload/v1621595108/postcube.cz/mobile-app03.png",
    "existing": false,
    "original_filename": "mobile-app03"
  },
  "mobile-app04.png": {
    "asset_id": "ccc5574f28228df367ba9b9f0f876c03",
    "public_id": "postcube.cz/mobile-app04",
    "version": 1621595110,
    "version_id": "7a6e2c61d96337570b0400bba12c1542",
    "signature": "dc5f484c35d09efa956ae807ee957529425017fd",
    "width": 1380,
    "height": 868,
    "format": "png",
    "resource_type": "image",
    "created_at": "2021-05-21T11:05:10Z",
    "tags": [],
    "bytes": 14164,
    "type": "upload",
    "etag": "5325d8fc93d6b5f617fc9b3d5fbca96d",
    "placeholder": false,
    "url": "http://res.cloudinary.com/topmonks/image/upload/v1621595110/postcube.cz/mobile-app04.png",
    "secure_url": "https://res.cloudinary.com/topmonks/image/upload/v1621595110/postcube.cz/mobile-app04.png",
    "existing": false,
    "original_filename": "mobile-app04"
  },
  "mobile-app05.png": {
    "asset_id": "619e8caa9cf58e5b800195a08e06c741",
    "public_id": "postcube.cz/mobile-app05",
    "version": 1621595112,
    "version_id": "d1aeaaa5a11a0aadde7901894e77b874",
    "signature": "1da5b97f5bfbb469c592cc360215cf5863e27b99",
    "width": 1380,
    "height": 868,
    "format": "png",
    "resource_type": "image",
    "created_at": "2021-05-21T11:05:12Z",
    "tags": [],
    "bytes": 7686,
    "type": "upload",
    "etag": "a43b3a9b0043847aac791c09b614fbc9",
    "placeholder": false,
    "url": "http://res.cloudinary.com/topmonks/image/upload/v1621595112/postcube.cz/mobile-app05.png",
    "secure_url": "https://res.cloudinary.com/topmonks/image/upload/v1621595112/postcube.cz/mobile-app05.png",
    "existing": false,
    "original_filename": "mobile-app05"
  },
  "mobile-app06.png": {
    "asset_id": "1c1de0b01fa84d1f3b2ddf9fe6d6eb57",
    "public_id": "postcube.cz/mobile-app06",
    "version": 1621595116,
    "version_id": "34341dffb25d5a300dde1fd9c440351b",
    "signature": "89b7de295f97411f16e2a41315176c8711af31c7",
    "width": 1380,
    "height": 868,
    "format": "png",
    "resource_type": "image",
    "created_at": "2021-05-21T11:05:16Z",
    "tags": [],
    "bytes": 10063,
    "type": "upload",
    "etag": "b94d05395d86c2428c5597e4b01ae766",
    "placeholder": false,
    "url": "http://res.cloudinary.com/topmonks/image/upload/v1621595116/postcube.cz/mobile-app06.png",
    "secure_url": "https://res.cloudinary.com/topmonks/image/upload/v1621595116/postcube.cz/mobile-app06.png",
    "existing": false,
    "original_filename": "mobile-app06"
  },
  "mobile-app01.svg": {
    "asset_id": "d1eb9ead901ba4e6e8da689a1d6786e7",
    "public_id": "postcube.cz/mobile-app01",
    "version": 1621595017,
    "version_id": "5c7075b7375e7063a253725e9dfa0990",
    "signature": "ab10a7998f23ee6ba675fe493ca7f63706af8cd4",
    "width": 1380,
    "height": 868,
    "format": "png",
    "resource_type": "image",
    "created_at": "2021-05-21T11:03:37Z",
    "tags": [],
    "bytes": 9768,
    "type": "upload",
    "placeholder": false,
    "url": "http://res.cloudinary.com/topmonks/image/upload/v1621595017/postcube.cz/mobile-app01.png",
    "secure_url": "https://res.cloudinary.com/topmonks/image/upload/v1621595017/postcube.cz/mobile-app01.png",
    "existing": true,
    "original_filename": "mobile-app01"
  },
  "mobile-app02.svg": {
    "asset_id": "a5dbd7118246abbedfb94073d9db2441",
    "public_id": "postcube.cz/mobile-app02",
    "version": 1621595106,
    "version_id": "9a6bda46d3cab1feb6fe6e1d395f0962",
    "signature": "93b2151dcb4bb2904db6e81a3d557d19e6637bff",
    "width": 1380,
    "height": 868,
    "format": "png",
    "resource_type": "image",
    "created_at": "2021-05-21T11:05:06Z",
    "tags": [],
    "bytes": 7686,
    "type": "upload",
    "placeholder": false,
    "url": "http://res.cloudinary.com/topmonks/image/upload/v1621595106/postcube.cz/mobile-app02.png",
    "secure_url": "https://res.cloudinary.com/topmonks/image/upload/v1621595106/postcube.cz/mobile-app02.png",
    "existing": true,
    "original_filename": "mobile-app02"
  },
  "mobile-app03.svg": {
    "asset_id": "203c5f44e7b104eaed84a6a67544378b",
    "public_id": "postcube.cz/mobile-app03",
    "version": 1621595108,
    "version_id": "7460d104134dc6fa8edf4471cd08eb0c",
    "signature": "ead58e5a68e5c541bd683294fd20848f70a081df",
    "width": 1380,
    "height": 868,
    "format": "png",
    "resource_type": "image",
    "created_at": "2021-05-21T11:05:08Z",
    "tags": [],
    "bytes": 7686,
    "type": "upload",
    "placeholder": false,
    "url": "http://res.cloudinary.com/topmonks/image/upload/v1621595108/postcube.cz/mobile-app03.png",
    "secure_url": "https://res.cloudinary.com/topmonks/image/upload/v1621595108/postcube.cz/mobile-app03.png",
    "existing": true,
    "original_filename": "mobile-app03"
  },
  "mobile-app04.svg": {
    "asset_id": "ccc5574f28228df367ba9b9f0f876c03",
    "public_id": "postcube.cz/mobile-app04",
    "version": 1621595110,
    "version_id": "7a6e2c61d96337570b0400bba12c1542",
    "signature": "dc5f484c35d09efa956ae807ee957529425017fd",
    "width": 1380,
    "height": 868,
    "format": "png",
    "resource_type": "image",
    "created_at": "2021-05-21T11:05:10Z",
    "tags": [],
    "bytes": 14164,
    "type": "upload",
    "placeholder": false,
    "url": "http://res.cloudinary.com/topmonks/image/upload/v1621595110/postcube.cz/mobile-app04.png",
    "secure_url": "https://res.cloudinary.com/topmonks/image/upload/v1621595110/postcube.cz/mobile-app04.png",
    "existing": true,
    "original_filename": "mobile-app04"
  },
  "mobile-app05.svg": {
    "asset_id": "619e8caa9cf58e5b800195a08e06c741",
    "public_id": "postcube.cz/mobile-app05",
    "version": 1621595112,
    "version_id": "d1aeaaa5a11a0aadde7901894e77b874",
    "signature": "1da5b97f5bfbb469c592cc360215cf5863e27b99",
    "width": 1380,
    "height": 868,
    "format": "png",
    "resource_type": "image",
    "created_at": "2021-05-21T11:05:12Z",
    "tags": [],
    "bytes": 7686,
    "type": "upload",
    "placeholder": false,
    "url": "http://res.cloudinary.com/topmonks/image/upload/v1621595112/postcube.cz/mobile-app05.png",
    "secure_url": "https://res.cloudinary.com/topmonks/image/upload/v1621595112/postcube.cz/mobile-app05.png",
    "existing": true,
    "original_filename": "mobile-app05"
  },
  "mobile-app06.svg": {
    "asset_id": "1c1de0b01fa84d1f3b2ddf9fe6d6eb57",
    "public_id": "postcube.cz/mobile-app06",
    "version": 1621595116,
    "version_id": "34341dffb25d5a300dde1fd9c440351b",
    "signature": "89b7de295f97411f16e2a41315176c8711af31c7",
    "width": 1380,
    "height": 868,
    "format": "png",
    "resource_type": "image",
    "created_at": "2021-05-21T11:05:16Z",
    "tags": [],
    "bytes": 10063,
    "type": "upload",
    "placeholder": false,
    "url": "http://res.cloudinary.com/topmonks/image/upload/v1621595116/postcube.cz/mobile-app06.png",
    "secure_url": "https://res.cloudinary.com/topmonks/image/upload/v1621595116/postcube.cz/mobile-app06.png",
    "existing": true,
    "original_filename": "mobile-app06"
  },
  "steps_bg.png": {
    "asset_id": "260c5fb886151e55a1e941e8a3767aa6",
    "public_id": "postcube.cz/steps_bg",
    "version": 1621864599,
    "version_id": "01f339a7013e51667e6c04307a23d8a7",
    "signature": "30561328fbd4a5f749e4b6e3ec016867a1bf8008",
    "width": 1380,
    "height": 868,
    "format": "png",
    "resource_type": "image",
    "created_at": "2021-05-24T13:56:39Z",
    "tags": [],
    "bytes": 7686,
    "type": "upload",
    "etag": "a43b3a9b0043847aac791c09b614fbc9",
    "placeholder": false,
    "url": "http://res.cloudinary.com/topmonks/image/upload/v1621864599/postcube.cz/steps_bg.png",
    "secure_url": "https://res.cloudinary.com/topmonks/image/upload/v1621864599/postcube.cz/steps_bg.png",
    "existing": false,
    "original_filename": "steps_bg"
  }
}